LICENSE
MANIFEST.in
requirements.txt
setup.py
test-requirements.txt
pydevinit/__init__.py
pydevinit.egg-info/PKG-INFO
pydevinit.egg-info/SOURCES.txt
pydevinit.egg-info/dependency_links.txt
pydevinit.egg-info/entry_points.txt
pydevinit.egg-info/not-zip-safe
pydevinit.egg-info/requires.txt
pydevinit.egg-info/top_level.txt
pydevinit/templates/project
pydevinit/templates/pydevproject