Metadata-Version: 1.1
Name: pydevinit
Version: 0.0.2
Summary: Eclipse PyDev Plugin Project Initialize Script
Home-page: https://github.com/momijiame/pydevinit
Author: momijiame
Author-email: amedama.ginmokusei@gmail.com
License: UNKNOWN
Platform: UNKNOWN
Classifier: Programming Language :: Python :: 2
Classifier: Programming Language :: Python :: 2.6
Classifier: Programming Language :: Python :: 2.7
Classifier: Programming Language :: Python :: 3
Classifier: Programming Language :: Python :: 3.3
Classifier: Development Status :: 3 - Alpha
Classifier: License :: OSI Approved :: Apache Software License
Classifier: Intended Audience :: Developers
Classifier: Natural Language :: Japanese
Classifier: Operating System :: POSIX
